gh_label_maker/__init__.py
gh_label_maker/cli.py
gh_label_maker/glm.py
gh_label_maker-0.0.2.dist-info/LICENSE
gh_label_maker-0.0.2.dist-info/METADATA
gh_label_maker-0.0.2.dist-info/WHEEL
gh_label_maker-0.0.2.dist-info/entry_points.txt
gh_label_maker-0.0.2.dist-info/top_level.txt
gh_label_maker-0.0.2.dist-info/RECORD
